featureflagclient/__init__.py
featureflagclient/client.py
tests/__init__.py
ffcharlietest-0.4.dist-info/LICENSE
ffcharlietest-0.4.dist-info/METADATA
ffcharlietest-0.4.dist-info/WHEEL
ffcharlietest-0.4.dist-info/top_level.txt
ffcharlietest-0.4.dist-info/RECORD
